pst.py
pst_format-1.1.1.data/scripts/pst
pst_format-1.1.1.data/scripts/pstf
pst_format-1.1.1.dist-info/DESCRIPTION.rst
pst_format-1.1.1.dist-info/METADATA
pst_format-1.1.1.dist-info/RECORD
pst_format-1.1.1.dist-info/WHEEL
pst_format-1.1.1.dist-info/metadata.json
pst_format-1.1.1.dist-info/top_level.txt
