Metadata-Version: 2.0
Name: pst-format
Version: 1.1.1
Summary: Plain Structured Text - data format suitable for I/O & command line
Home-page: https://github.com/peterkuma/pst
Author: Peter Kuma
Author-email: peter.kuma@fastmail.com
License: Public Domain
Platform: UNKNOWN
Classifier: Development Status :: 5 - Production/Stable
Classifier: Environment :: Console
Classifier: Operating System :: OS Independent
Classifier: Programming Language :: Python :: 2.7
Classifier: Programming Language :: Python :: 3
Classifier: Topic :: Text Processing :: Markup
Classifier: Topic :: Utilities
